gImageGrabber-0.1.15.data/data/driver/chromedriver.exe
gImageGrabber-0.1.15.data/data/driver/geckodriver
gImageGrabber-0.1.15.data/data/driver/geckodriver.exe
gImageGrabber-0.1.15.data/scripts/simpleScript.py
imggrabber/__init__.py
imggrabber/imgScrape.py
imggrabber/imgTools.py
gImageGrabber-0.1.15.dist-info/LICENSE.txt
gImageGrabber-0.1.15.dist-info/METADATA
gImageGrabber-0.1.15.dist-info/WHEEL
gImageGrabber-0.1.15.dist-info/top_level.txt
gImageGrabber-0.1.15.dist-info/RECORD
