Metadata-Version: 2.1
Name: gImageGrabber
Version: 0.1.15
Summary: Tools to download images from Google search
Home-page: https://pypi.org/project/gImageGrabber
Author: Saksham Sharma
Author-email: codeck313@gmail.com
License: GNU General Public License version 3
Project-URL: gImageGrabber Source, https://github.com/codeck313/gImageGrabber
Keywords: google images extractor parser webpage gImageGrabber grabber extract search image python
Platform: UNKNOWN
Classifier: Intended Audience :: Science/Research
Classifier: Intended Audience :: Developers
Classifier: Intended Audience :: Education
Classifier: License :: OSI Approved :: GNU General Public License v3 or later (GPLv3+)
Classifier: Programming Language :: Python :: 3
Classifier: Operating System :: Microsoft :: Windows :: Windows 10
Classifier: Operating System :: POSIX :: Linux
Classifier: Natural Language :: English
Classifier: Topic :: Scientific/Engineering :: Information Analysis
Classifier: Topic :: Scientific/Engineering :: Image Recognition
Classifier: Topic :: Utilities
Requires-Dist: urllib3 (==1.24.2)
Requires-Dist: beautifulsoup4 (==4.6.3)
Requires-Dist: selenium (==3.14.1)
